scrapy_beautifulsoup/__init__.py
scrapy_beautifulsoup/middleware.py
scrapy_beautifulsoup-0.0.2.dist-info/DESCRIPTION.rst
scrapy_beautifulsoup-0.0.2.dist-info/METADATA
scrapy_beautifulsoup-0.0.2.dist-info/RECORD
scrapy_beautifulsoup-0.0.2.dist-info/WHEEL
scrapy_beautifulsoup-0.0.2.dist-info/metadata.json
scrapy_beautifulsoup-0.0.2.dist-info/top_level.txt
