Metadata-Version: 1.1
Name: scrapy-beautifulsoup
Version: 0.0.2
Summary: Simple Scrapy middleware to process non-well-formed HTML with BeautifulSoup
Home-page: https://github.com/alecxe/scrapy-beautifulsoup
Author: Alexander Afanasyev
Author-email: afanasieffav@gmail.com
License: New BSD License
Keywords: scrapy beautifulsoup html html-parsing web-scraping
Platform: UNKNOWN
Classifier: Development Status :: 4 - Beta
Classifier: Framework :: Scrapy
Classifier: Intended Audience :: Developers
Classifier: License :: OSI Approved :: BSD License
Classifier: Programming Language :: Python
Classifier: Topic :: Internet :: WWW/HTTP
